[
    {
        "uprCd": "6440000",
        "orgCd": "5580000",
        "orgdownNm": "계룡시"
    },
    {
        "uprCd": "6440000",
        "orgCd": "4500000",
        "orgdownNm": "공주시"
    },
    {
        "uprCd": "6440000",
        "orgCd": "4550000",
        "orgdownNm": "금산군"
    },
    {
        "uprCd": "6440000",
        "orgCd": "4540000",
        "orgdownNm": "논산시"
    },
    {
        "uprCd": "6440000",
        "orgCd": "5680000",
        "orgdownNm": "당진시"
    },
    {
        "uprCd": "6440000",
        "orgCd": "4510000",
        "orgdownNm": "보령시"
    },
    {
        "uprCd": "6440000",
        "orgCd": "4570000",
        "orgdownNm": "부여군"
    },
    {
        "uprCd": "6440000",
        "orgCd": "4530000",
        "orgdownNm": "서산시"
    },
    {
        "uprCd": "6440000",
        "orgCd": "4580000",
        "orgdownNm": "서천군"
    },
    {
        "uprCd": "6440000",
        "orgCd": "4520000",
        "orgdownNm": "아산시"
    },
    {
        "uprCd": "6440000",
        "orgCd": "4610000",
        "orgdownNm": "예산군"
    },
    {
        "uprCd": "6440000",
        "orgCd": "4490000",
        "orgdownNm": "천안시"
    },
    {
        "uprCd": "6440000",
        "orgCd": "4590000",
        "orgdownNm": "청양군"
    },
    {
        "uprCd": "6440000",
        "orgCd": "4620000",
        "orgdownNm": "태안군"
    },
    {
        "uprCd": "6440000",
        "orgCd": "4600000",
        "orgdownNm": "홍성군"
    }
]